README.txt
setup.cfg
setup.py
docs/HISTORY.txt
getpaid/__init__.py
getpaid.paymentprocessors.egg-info/PKG-INFO
getpaid.paymentprocessors.egg-info/SOURCES.txt
getpaid.paymentprocessors.egg-info/dependency_links.txt
getpaid.paymentprocessors.egg-info/entry_points.txt
getpaid.paymentprocessors.egg-info/namespace_packages.txt
getpaid.paymentprocessors.egg-info/not-zip-safe
getpaid.paymentprocessors.egg-info/requires.txt
getpaid.paymentprocessors.egg-info/top_level.txt
getpaid/paymentprocessors/__init__.py
getpaid/paymentprocessors/configure.zcml
getpaid/paymentprocessors/directives.py
getpaid/paymentprocessors/i18n.sh
getpaid/paymentprocessors/interfaces.py
getpaid/paymentprocessors/meta.zcml
getpaid/paymentprocessors/paymentinfo.py
getpaid/paymentprocessors/registry.py
getpaid/paymentprocessors/vocabularies.py
getpaid/paymentprocessors/locales/getpaid.paymentprocessors.pot
getpaid/paymentprocessors/locales/manual.pot
getpaid/paymentprocessors/tests/__init__.py
getpaid/paymentprocessors/tests/base.py
getpaid/paymentprocessors/tests/dummies.py
getpaid/paymentprocessors/tests/test_payment.py
getpaid/paymentprocessors/tests/test_views.py
getpaid/paymentprocessors/tests/test_zcml.py
getpaid/paymentprocessors/tests/templates/button.pt
getpaid/paymentprocessors/tests/templates/thank_you.pt