Metadata-Version: 1.0
Name: getpaid.paymentprocessors
Version: 0.1
Summary: Support multiple payment processors on GetPaid site
Home-page: http://www.plonegetpaid.com
Author: Getpaid Community
Author-email: getpaid-dev@googlegroups.com
License: BSD
Platform: UNKNOWN
Classifier: Programming Language :: Python
Classifier: Topic :: Software Development :: Libraries :: Python Modules
